{
  "lastModified": 1650309907000,
  "powercuts": {
    "INCD-286867-A": {
      "areacode": 23,
      "category": "U/G Service repair",
      "class": "models.MapDataPowercutIncno",
      "contact": "BARRATT, GEOFF",
      "customerStageSequence": 4,
      "elapsed": "00d 07:51",
      "estimatedTimeTillResolution": null,
      "group": "RESTORATION",
      "latestStageSequenceHistory": 1650302708000,
      "latestStageSequenceStatus": 4,
      "location": "DN9 3AA, OLD STATION YARD, STATION ROAD, BLAXTON, DONCASTER",
      "logged": 1650281640000,
      "natureOfOutage": "Localised Fault",
      "networkObject": "4055169",
      "numberOfCalls": 1,
      "postcodes": {
        "DN9 3AA": {
          "class": "models.MapDataLocation",
          "lat": 53.4894,
          "lng": -0.990904
        }
      },
      "prefix": null,
      "priority": 4,
      "reference": "INCD-286867-A",
      "region": "South Yorkshire / Doncaster 1",
      "resourceAllocationDelay": 0,
      "stageSequence": 4,
      "startnumber": 0,
      "status": "In Progress",
      "totalConfirmedOff": 1,
      "totalPredictedOff": 0,
      "totalResourceAssigned": 0,
      "totalResourceDispatched": 0,
      "totalResourceOnsite": 1,
      "totalRestored": 0,
      "totalSensitiveAffected": 0,
      "type": "LV",
      "hoursSinceLogged": 7,
      "stageSequenceMessage": "Our team are working hard to restore your power as quickly as possible",
      "categoryWebText": "The power cut affecting your property has been caused by an unexpected problem with the cables or equipment that serve your area. If you need to report an emergency, please call 105"
    },
    "INCD-286892-A": {
      "areacode": 23,
      "category": "U/G Service repair",
      "class": "models.MapDataPowercutIncno",
      "contact": "LEDGER, GAVIN",
      "customerStageSequence": 4,
      "elapsed": "00d 04:20",
      "estimatedTimeTillResolution": null,
      "group": "RESTORATION",
      "latestStageSequenceHistory": 1650299406000,
      "latestStageSequenceStatus": 3,
      "location": "HD4 5UE, 95, COWLERSLEY LANE, HUDDERSFIELD",
      "logged": 1650294300000,
      "natureOfOutage": "Localised Fault",
      "networkObject": "4067012",
      "numberOfCalls": 1,
      "postcodes": {
        "HD4 5UE": {
          "class": "models.MapDataLocation",
          "lat": 53.6352,
          "lng": -1.8364
        }
      },
      "prefix": null,
      "priority": 3,
      "reference": "INCD-286892-A",
      "region": "West Yorkshire / Leeds South 1",
      "resourceAllocationDelay": 0,
      "stageSequence": 3,
      "startnumber": 0,
      "status": "In Progress",
      "totalConfirmedOff": 1,
      "totalPredictedOff": 0,
      "totalResourceAssigned": 0,
      "totalResourceDispatched": 1,
      "totalResourceOnsite": 0,
      "totalRestored": 0,
      "totalSensitiveAffected": 1,
      "type": "LV",
      "hoursSinceLogged": 4,
      "stageSequenceMessage": "Our team are working hard to restore your power as quickly as possible",
      "categoryWebText": "The power cut affecting your property has been caused by an unexpected problem with the cables or equipment that serve your area. If you need to report an emergency, please call 105"
    },
    "INCD-286901-A": {
      "areacode": 23,
      "category": "U/G Service repair",
      "class": "models.MapDataPowercutIncno",
      "contact": "COOPER, SONNY",
      "customerStageSequence": 5,
      "elapsed": "00d 02:29",
      "estimatedTimeTillResolution": 1650312900000,
      "group": "RESTORATION",
      "latestStageSequenceHistory": 1650308709000,
      "latestStageSequenceStatus": 5,
      "location": "S35 9WR, CROSS HILL SS, Transformer LV",
      "logged": 1650300960000,
      "natureOfOutage": "Localised Fault",
      "networkObject": "4072488",
      "numberOfCalls": 2,
      "postcodes": {
        "S35 9WL": {
          "class": "models.MapDataLocation",
          "lat": 53.44,
          "lng": -1.4574
        },
        "S35 9XB": {
          "class": "models.MapDataLocation",
          "lat": 53.438,
          "lng": -1.46048
        },
        "S35 9WR": {
          "class": "models.MapDataLocation",
          "lat": 53.438,
          "lng": -1.45817
        },
        "S35 9WS": {
          "class": "models.MapDataLocation",
          "lat": 53.4355,
          "lng": -1.45796
        },
        "S35 9WT": {
          "class": "models.MapDataLocation",
          "lat": 53.4384,
          "lng": -1.45864
        },
        "S35 9YS": {
          "class": "models.MapDataLocation",
          "lat": 53.4367,
          "lng": -1.45823
        },
        "S35 9XF": {
          "class": "models.MapDataLocation",
          "lat": 53.4375,
          "lng": -1.45957
        },
        "S30 3WS": {
          "class": "models.MapDataLocation",
          "lat": 53.4355,
          "lng": -1.45797
        },
        "S35 9TU": {
          "class": "models.MapDataLocation",
          "lat": 53.4369,
          "lng": -1.45877
        }
      },
      "prefix": null,
      "priority": 4,
      "reference": "INCD-286901-A",
      "region": "South Yorkshire / Sheffield 1",
      "resourceAllocationDelay": 0,
      "stageSequence": 5,
      "startnumber": 0,
      "status": "In Progress",
      "totalConfirmedOff": 4,
      "totalPredictedOff": 120,
      "totalResourceAssigned": 0,
      "totalResourceDispatched": 1,
      "totalResourceOnsite": 2,
      "totalRestored": 0,
      "totalSensitiveAffected": 23,
      "type": "LV",
      "hoursSinceLogged": 2,
      "stageSequenceMessage": "Our team are working hard to restore your power as quickly as possible",
      "categoryWebText": "The power cut affecting your property has been caused by an unexpected problem with the cables or equipment that serve your area. If you need to report an emergency, please call 105"
    },
    "INCD-286905-A": {
      "areacode": 23,
      "category": "Unknown P2",
      "class": "models.MapDataPowercutIncno",
      "contact": "MARTIN, WAYNE",
      "customerStageSequence": 3,
      "elapsed": "00d 02:05",
      "estimatedTimeTillResolution": 1650313800000,
      "group": "RESTORATION",
      "latestStageSequenceHistory": 1650304207000,
      "latestStageSequenceStatus": 3,
      "location": "DN21 1SG, GAINSBOROUGH RISEHOLME SS, Transformer LV",
      "logged": 1650302400000,
      "natureOfOutage": "Localised Fault",
      "networkObject": "4048684",
      "numberOfCalls": 5,
      "postcodes": {
        "DN21 1YZ": {
          "class": "models.MapDataLocation",
          "lat": 53.3922,
          "lng": -0.750719
        },
        "DN21 1SA": {
          "class": "models.MapDataLocation",
          "lat": 53.3921,
          "lng": -0.751565
        },
        "DN21 1YY": {
          "class": "models.MapDataLocation",
          "lat": 53.3927,
          "lng": -0.751772
        },
        "DN21 1SB": {
          "class": "models.MapDataLocation",
          "lat": 53.3915,
          "lng": -0.750768
        },
        "DN21 1YX": {
          "class": "models.MapDataLocation",
          "lat": 53.393,
          "lng": -0.752876
        },
        "DN21 1SD": {
          "class": "models.MapDataLocation",
          "lat": 53.3921,
          "lng": -0.749487
        }
      },
      "prefix": null,
      "priority": 4,
      "reference": "INCD-286905-A",
      "region": "North Lincolnshire / Scunthorpe 2",
      "resourceAllocationDelay": 0,
      "stageSequence": 3,
      "startnumber": 0,
      "status": "In Progress",
      "totalConfirmedOff": 0,
      "totalPredictedOff": 121,
      "totalResourceAssigned": 0,
      "totalResourceDispatched": 1,
      "totalResourceOnsite": 0,
      "totalRestored": 0,
      "totalSensitiveAffected": 17,
      "type": "LV",
      "hoursSinceLogged": 2,
      "stageSequenceMessage": "Our team are working hard to restore your power as quickly as possible",
      "categoryWebText": "The power cut affecting your property has been caused by an unexpected problem with the cables or equipment that serve your area. If you need to report an emergency, please call 105"
    },
    "INCD-286909-A": {
      "areacode": 23,
      "category": "Unknown P2",
      "class": "models.MapDataPowercutIncno",
      "contact": "MORGAN, DAVID",
      "customerStageSequence": 5,
      "elapsed": "00d 01:40",
      "estimatedTimeTillResolution": 1650315600000,
      "group": "RESTORATION",
      "latestStageSequenceHistory": 1650309908000,
      "latestStageSequenceStatus": 5,
      "location": "LS11 6JT, DEWSBURY ROAD FIRE STATION SS, Transformer LV",
      "logged": 1650303900000,
      "natureOfOutage": "Localised Fault",
      "networkObject": "4044939",
      "numberOfCalls": 9,
      "postcodes": {
        "LS11 6JT": {
          "class": "models.MapDataLocation",
          "lat": 53.7736,
          "lng": -1.54709
        },
        "LS11 5LQ": {
          "class": "models.MapDataLocation",
          "lat": 53.7713,
          "lng": -1.54874
        },
        "LS11 5HS": {
          "class": "models.MapDataLocation",
          "lat": 53.7743,
          "lng": -1.54486
        },
        "LS11 5HR": {
          "class": "models.MapDataLocation",
          "lat": 53.7739,
          "lng": -1.54522
        },
        "LS11 5HP": {
          "class": "models.MapDataLocation",
          "lat": 53.7748,
          "lng": -1.54321
        }
      },
      "prefix": null,
      "priority": 3,
      "reference": "INCD-286909-A",
      "region": "West Yorkshire / Leeds North 1",
      "resourceAllocationDelay": 0,
      "stageSequence": 5,
      "startnumber": 0,
      "status": "In Progress",
      "totalConfirmedOff": 34,
      "totalPredictedOff": 0,
      "totalResourceAssigned": 0,
      "totalResourceDispatched": 1,
      "totalResourceOnsite": 2,
      "totalRestored": 0,
      "totalSensitiveAffected": 4,
      "type": "LV",
      "hoursSinceLogged": 1,
      "stageSequenceMessage": "Our team are working hard to restore your power as quickly as possible",
      "categoryWebText": "The power cut affecting your property has been caused by an unexpected problem with the cables or equipment that serve your area. If you need to report an emergency, please call 105"
    },
    "INCD-286915-A": {
      "areacode": 15,
      "category": "Unknown P2",
      "class": "models.MapDataPowercutIncno",
      "contact": "LUTHER, MARC",
      "customerStageSequence": 4,
      "elapsed": "00d 00:53",
      "estimatedTimeTillResolution": 1650318300000,
      "group": "RESTORATION",
      "latestStageSequenceHistory": 1650308709000,
      "latestStageSequenceStatus": 4,
      "location": "NE23 8EJ, 23, LINDSEY CLOSE, CRAMLINGTON",
      "logged": 1650306720000,
      "natureOfOutage": "Single Premise",
      "networkObject": "CRAMLINGTON",
      "numberOfCalls": 1,
      "postcodes": {
        "NE23 8EJ": {
          "class": "models.MapDataLocation",
          "lat": 55.0846,
          "lng": -1.60314
        }
      },
      "prefix": null,
      "priority": 4,
      "reference": "INCD-286915-A",
      "region": "Tyne and Wear / Newcastle 2",
      "resourceAllocationDelay": 0,
      "stageSequence": 4,
      "startnumber": 0,
      "status": "In Progress",
      "totalConfirmedOff": 0,
      "totalPredictedOff": 1,
      "totalResourceAssigned": 0,
      "totalResourceDispatched": 0,
      "totalResourceOnsite": 1,
      "totalRestored": 0,
      "totalSensitiveAffected": 0,
      "type": "SP",
      "hoursSinceLogged": 0,
      "stageSequenceMessage": "Our team are working hard to restore your power as quickly as possible",
      "categoryWebText": "The power cut affecting your property has been caused by an unexpected problem with the cables or equipment that serve your area. If you need to report an emergency, please call 105"
    },
    "INCD-286916-A": {
      "areacode": 15,
      "category": "Unknown P2",
      "class": "models.MapDataPowercutIncno",
      "contact": "UTLEY, CHRIS",
      "customerStageSequence": 3,
      "elapsed": "00d 00:42",
      "estimatedTimeTillResolution": 1650318300000,
      "group": "RESTORATION",
      "latestStageSequenceHistory": 1650307806000,
      "latestStageSequenceStatus": 3,
      "location": "DL10 5JF, 14, HIGH STREET, GILLING WEST, RICHMOND",
      "logged": 1650307380000,
      "natureOfOutage": "Single Premise",
      "networkObject": "CATTERICK CAMP",
      "numberOfCalls": 1,
      "postcodes": {
        "DL10 5JF": {
          "class": "models.MapDataLocation",
          "lat": 54.44,
          "lng": -1.71954
        }
      },
      "prefix": null,
      "priority": 4,
      "reference": "INCD-286916-A",
      "region": "Yorkshire Dales NE / Northallerton 1",
      "resourceAllocationDelay": 0,
      "stageSequence": 3,
      "startnumber": 0,
      "status": "In Progress",
      "totalConfirmedOff": 0,
      "totalPredictedOff": 1,
      "totalResourceAssigned": 0,
      "totalResourceDispatched": 1,
      "totalResourceOnsite": 0,
      "totalRestored": 0,
      "totalSensitiveAffected": 0,
      "type": "SP",
      "hoursSinceLogged": 0,
      "stageSequenceMessage": "Our team are working hard to restore your power as quickly as possible",
      "categoryWebText": "The power cut affecting your property has been caused by an unexpected problem with the cables or equipment that serve your area. If you need to report an emergency, please call 105"
    },
    "INCD-286917-A": {
      "areacode": 23,
      "category": "Unknown P2",
      "class": "models.MapDataPowercutIncno",
      "contact": "STRATHEARN, MATTHEW",
      "customerStageSequence": 3,
      "elapsed": "00d 00:41",
      "estimatedTimeTillResolution": 1650318300000,
      "group": "RESTORATION",
      "latestStageSequenceHistory": 1650307806000,
      "latestStageSequenceStatus": 3,
      "location": "HU11 5QW, CATWICK NORTH, ARCB",
      "logged": 1650307440000,
      "natureOfOutage": "Large Area Fault",
      "networkObject": "4043400-ASSET",
      "numberOfCalls": 11,
      "postcodes": {
        "HU17 5PW": {
          "class": "models.MapDataLocation",
          "lat": 53.8917,
          "lng": -0.282107
        },
        "HU17 5LY": {
          "class": "models.MapDataLocation",
          "lat": 53.8909,
          "lng": -0.323469
        },
        "HU17 5LX": {
          "class": "models.MapDataLocation",
          "lat": 53.8894,
          "lng": -0.319316
        },
        "HU17 5NP": {
          "class": "models.MapDataLocation",
          "lat": 53.8893,
          "lng": -0.314648
        },
        "HU17 5PT": {
          "class": "models.MapDataLocation",
          "lat": 53.8936,
          "lng": -0.291557
        },
        "HU17 5NN": {
          "class": "models.MapDataLocation",
          "lat": 53.8903,
          "lng": -0.311763
        },
        "HU17 5PS": {
          "class": "models.MapDataLocation",
          "lat": 53.8861,
          "lng": -0.285562
        },
        "HU17 5NU": {
          "class": "models.MapDataLocation",
          "lat": 53.8913,
          "lng": -0.315265
        },
        "HU17 5PR": {
          "class": "models.MapDataLocation",
          "lat": 53.8909,
          "lng": -0.285351
        },
        "HU17 5NT": {
          "class": "models.MapDataLocation",
          "lat": 53.8922,
          "lng": -0.315399
        },
        "HU17 5NS": {
          "class": "models.MapDataLocation",
          "lat": 53.8921,
          "lng": -0.312223
        },
        "HU17 5PP": {
          "class": "models.MapDataLocation",
          "lat": 53.8905,
          "lng": -0.282035
        },
        "HU17 5NR": {
          "class": "models.MapDataLocation",
          "lat": 53.8916,
          "lng": -0.313109
        },
        "HU17 5PN": {
          "class": "models.MapDataLocation",
          "lat": 53.8842,
          "lng": -0.270727
        },
        "HU17 5NG": {
          "class": "models.MapDataLocation",
          "lat": 53.8928,
          "lng": -0.313318
        },
        "HU17 5PL": {
          "class": "models.MapDataLocation",
          "lat": 53.892,
          "lng": -0.278063
        },
        "HU17 5NF": {
          "class": "models.MapDataLocation",
          "lat": 53.8933,
          "lng": -0.317773
        },
        "HU17 5PJ": {
          "class": "models.MapDataLocation",
          "lat": 53.8933,
          "lng": -0.281691
        },
        "HU17 5NL": {
          "class": "models.MapDataLocation",
          "lat": 53.8909,
          "lng": -0.312833
        },
        "HU17 5PH": {
          "class": "models.MapDataLocation",
          "lat": 53.8934,
          "lng": -0.283088
        },
        "HU17 5NJ": {
          "class": "models.MapDataLocation",
          "lat": 53.8928,
          "lng": -0.306366
        },
        "HU17 5LH": {
          "class": "models.MapDataLocation",
          "lat": 53.8914,
          "lng": -0.318901
        },
        "HU17 5QE": {
          "class": "models.MapDataLocation",
          "lat": 53.887,
          "lng": -0.312475
        },
        "HU17 5QF": {
          "class": "models.MapDataLocation",
          "lat": 53.8881,
          "lng": -0.312732
        },
        "HU17 5QD": {
          "class": "models.MapDataLocation",
          "lat": 53.8876,
          "lng": -0.312569
        },
        "HU17 5LE": {
          "class": "models.MapDataLocation",
          "lat": 53.8923,
          "lng": -0.320933
        },
        "HU17 5QA": {
          "class": "models.MapDataLocation",
          "lat": 53.8886,
          "lng": -0.313232
        },
        "HU17 5LF": {
          "class": "models.MapDataLocation",
          "lat": 53.8926,
          "lng": -0.320618
        },
        "HU17 5LG": {
          "class": "models.MapDataLocation",
          "lat": 53.891,
          "lng": -0.320271
        },
        "HU17 5NX": {
          "class": "models.MapDataLocation",
          "lat": 53.8905,
          "lng": -0.315848
        },
        "YO25 8RU": {
          "class": "models.MapDataLocation",
          "lat": 53.9026,
          "lng": -0.311615
        },
        "HU17 5LQ": {
          "class": "models.MapDataLocation",
          "lat": 53.8903,
          "lng": -0.318745
        },
        "HU17 5NY": {
          "class": "models.MapDataLocation",
          "lat": 53.8878,
          "lng": -0.316153
        },
        "HU17 5NW": {
          "class": "models.MapDataLocation",
          "lat": 53.8879,
          "lng": -0.314797
        },
        "YO25 8RT": {
          "class": "models.MapDataLocation",
          "lat": 53.9071,
          "lng": -0.304175
        },
        "HU17 5NZ": {
          "class": "models.MapDataLocation",
          "lat": 53.8906,
          "lng": -0.316968
        },
        "YO25 9SU": {
          "class": "models.MapDataLocation",
          "lat": 53.909,
          "lng": -0.484803
        },
        "HU17 7PG": {
          "class": "models.MapDataLocation",
          "lat": 53.8778,
          "lng": -0.513037
        },
        "HU17 5NE": {
          "class": "models.MapDataLocation",
          "lat": 53.891,
          "lng": -0.310396
        },
        "HU17 5ND": {
          "class": "models.MapDataLocation",
          "lat": 53.8889,
          "lng": -0.315289
        },
        "YO25 8SB": {
          "class": "models.MapDataLocation",
          "lat": 53.9027,
          "lng": -0.283758
        },
        "HU17 5NB": {
          "class": "models.MapDataLocation",
          "lat": 53.8897,
          "lng": -0.319606
        },
        "HU11 5QW": {
          "class": "models.MapDataLocation",
          "lat": 53.898,
          "lng": -0.275578
        }
      },
      "prefix": null,
      "priority": 2,
      "reference": "INCD-286917-A",
      "region": "Humber Estuary / Hull 1",
      "resourceAllocationDelay": 0,
      "stageSequence": 3,
      "startnumber": 0,
      "status": "In Progress",
      "totalConfirmedOff": 0,
      "totalPredictedOff": 847,
      "totalResourceAssigned": 0,
      "totalResourceDispatched": 2,
      "totalResourceOnsite": 0,
      "totalRestored": 0,
      "totalSensitiveAffected": 129,
      "type": "HV_N",
      "hoursSinceLogged": 0,
      "stageSequenceMessage": "Our team are working hard to restore your power as quickly as possible",
      "categoryWebText": "The power cut affecting your property has been caused by an unexpected problem with the cables or equipment that serve your area. If you need to report an emergency, please call 105"
    },
    "INCD-286919-A": {
      "areacode": 23,
      "category": "Unknown P2",
      "class": "models.MapDataPowercutIncno",
      "contact": "",
      "customerStageSequence": 1,
      "elapsed": "00d 00:37",
      "estimatedTimeTillResolution": 1650319200000,
      "group": "RESTORATION",
      "latestStageSequenceHistory": 1650307806000,
      "latestStageSequenceStatus": 1,
      "location": "S35 1YX, 14, GLENWOOD CRESCENT, CHAPELTOWN, SHEFFIELD",
      "logged": 1650307680000,
      "natureOfOutage": "Single Premise",
      "networkObject": "ECCLESFIELD",
      "numberOfCalls": 1,
      "postcodes": {
        "S35 1YX": {
          "class": "models.MapDataLocation",
          "lat": 53.4601,
          "lng": -1.46082
        }
      },
      "prefix": null,
      "priority": 4,
      "reference": "INCD-286919-A",
      "region": "South Yorkshire / Sheffield 1",
      "resourceAllocationDelay": 0,
      "stageSequence": 1,
      "startnumber": 0,
      "status": "Awaiting",
      "totalConfirmedOff": 0,
      "totalPredictedOff": 1,
      "totalResourceAssigned": 0,
      "totalResourceDispatched": 0,
      "totalResourceOnsite": 0,
      "totalRestored": 0,
      "totalSensitiveAffected": 0,
      "type": "SP",
      "hoursSinceLogged": 0,
      "stageSequenceMessage": "Our team are working hard to restore your power as quickly as possible",
      "categoryWebText": "The power cut affecting your property has been caused by an unexpected problem with the cables or equipment that serve your area. If you need to report an emergency, please call 105"
    },
    "INCD-286924-A": {
      "areacode": 23,
      "category": "Unknown P2",
      "class": "models.MapDataPowercutIncno",
      "contact": "SHIELDS, CRAIG",
      "customerStageSequence": 3,
      "elapsed": "00d 00:29",
      "estimatedTimeTillResolution": 1650319200000,
      "group": "RESTORATION",
      "latestStageSequenceHistory": 1650309908000,
      "latestStageSequenceStatus": 3,
      "location": "WF10 1EF, 127-129, NOBLES AMUSEMENTS, CARLTON STREET, CASTLEFORD",
      "logged": 1650308160000,
      "natureOfOutage": "Single Premise",
      "networkObject": "WELLINGTON STREET",
      "numberOfCalls": 1,
      "postcodes": {
        "WF10 1EF": {
          "class": "models.MapDataLocation",
          "lat": 53.7255,
          "lng": -1.35583
        }
      },
      "prefix": null,
      "priority": 4,
      "reference": "INCD-286924-A",
      "region": "West Yorkshire / Castleford 2",
      "resourceAllocationDelay": 0,
      "stageSequence": 3,
      "startnumber": 0,
      "status": "In Progress",
      "totalConfirmedOff": 0,
      "totalPredictedOff": 1,
      "totalResourceAssigned": 0,
      "totalResourceDispatched": 1,
      "totalResourceOnsite": 0,
      "totalRestored": 0,
      "totalSensitiveAffected": 0,
      "type": "SP",
      "hoursSinceLogged": 0,
      "stageSequenceMessage": "Our team are working hard to restore your power as quickly as possible",
      "categoryWebText": "The power cut affecting your property has been caused by an unexpected problem with the cables or equipment that serve your area. If you need to report an emergency, please call 105"
    },
    "PPC044464": {
      "areacode": 23,
      "category": "We need to temporarily turn the power off to carry out maintenance on our network in the area.",
      "class": "models.MapDataPowercutIncno",
      "contact": "Sam Keyworth",
      "customerStageSequence": 7,
      "elapsed": "0d 11:25",
      "estimatedTimeTillResolution": 1650283200000,
      "group": "RESTORATION",
      "latestStageSequenceHistory": 1650283206000,
      "latestStageSequenceStatus": 5,
      "location": "Flixborough - Neap House - Sorrel Way",
      "logged": 1650268800000,
      "natureOfOutage": "Planned Work on System",
      "networkObject": "FLIXBOROUGH WHARF 5008",
      "numberOfCalls": 0,
      "postcodes": {
        "DN15 8AN": {
          "class": "models.MapDataLocation",
          "lat": 53.593,
          "lng": -0.680136
        },
        "DN15 8UE": {
          "class": "models.MapDataLocation",
          "lat": 53.6089,
          "lng": -0.700318
        },
        "DN15 8UF": {
          "class": "models.MapDataLocation",
          "lat": 53.6018,
          "lng": -0.686375
        },
        "DN15 8UA": {
          "class": "models.MapDataLocation",
          "lat": 53.6058,
          "lng": -0.718278
        },
        "DN15 8EQ": {
          "class": "models.MapDataLocation",
          "lat": 53.6009,
          "lng": -0.676762
        },
        "DN15 8SH": {
          "class": "models.MapDataLocation",
          "lat": 53.6237,
          "lng": -0.696975
        },
        "DN15 8UG": {
          "class": "models.MapDataLocation",
          "lat": 53.6018,
          "lng": -0.685044
        },
        "DN15 8DT": {
          "class": "models.MapDataLocation",
          "lat": 53.597,
          "lng": -0.682445
        },
        "DN15 8UJ": {
          "class": "models.MapDataLocation",
          "lat": 53.6088,
          "lng": -0.699701
        },
        "DN15 8SN": {
          "class": "models.MapDataLocation",
          "lat": 53.6189,
          "lng": -0.697832
        },
        "DN17 2HG": {
          "class": "models.MapDataLocation",
          "lat": 53.5611,
          "lng": -0.674953
        },
        "DN15 8UR": {
          "class": "models.MapDataLocation",
          "lat": 53.6021,
          "lng": -0.682134
        },
        "DN15 8UQ": {
          "class": "models.MapDataLocation",
          "lat": 53.6025,
          "lng": -0.685145
        },
        "DN15 8UP": {
          "class": "models.MapDataLocation",
          "lat": 53.6027,
          "lng": -0.681284
        },
        "DN14 8HD": {
          "class": "models.MapDataLocation",
          "lat": 53.6979,
          "lng": -0.790608
        },
        "DN15 8ND": {
          "class": "models.MapDataLocation",
          "lat": 53.5964,
          "lng": -0.666762
        },
        "DN15 8TX": {
          "class": "models.MapDataLocation",
          "lat": 53.6035,
          "lng": -0.712348
        }
      },
      "prefix": null,
      "priority": 8,
      "reference": "PPC044464",
      "region": "Flixborough - Neap House - Sorrel Way",
      "resourceAllocationDelay": 0,
      "stageSequence": 5,
      "startnumber": 0,
      "status": "The scheduled work has now been completed",
      "totalConfirmedOff": 82,
      "totalPredictedOff": 0,
      "totalResourceAssigned": 0,
      "totalResourceDispatched": 0,
      "totalResourceOnsite": 0,
      "totalRestored": 0,
      "totalSensitiveAffected": 13,
      "type": "LV",
      "hoursSinceLogged": 11,
      "stageSequenceMessage": "",
      "categoryWebText": ""
    }
  }
}
